{
  "schemaVersion": 1,
  "pairId": "NS_USDC",
  "week": {
    "weekYear": 2026,
    "week": 27,
    "startsAt": "2026-06-29T00:00:00.000Z",
    "endsAt": "2026-07-06T00:00:00.000Z",
    "timeZone": "UTC"
  },
  "barIntervalMinutes": 5,
  "priceConvention": "USDC_PER_BASE",
  "disclaimer": "USDC is a token-denominated reference asset in this repository. It is not fiat USD and this repository does not guarantee a USDC/USD peg.",
  "bars": [
    {
      "start": "2026-06-29T00:00:00.000Z",
      "end": "2026-06-29T00:05:00.000Z",
      "status": "filled",
      "eventCount": 1,
      "open": "0.01082",
      "high": "0.01082",
      "low": "0.01082",
      "close": "0.01082",
      "baseVolumeAtomic": "410000000",
      "quoteVolumeAtomic": "4436200"
    },
    {
      "start": "2026-06-29T00:05:00.000Z",
      "end": "2026-06-29T00:10:00.000Z",
      "status": "empty",
      "eventCount": 0,
      "open": null,
      "high": null,
      "low": null,
      "close": null,
      "baseVolumeAtomic": "0",
      "quoteVolumeAtomic": "0"
    },
    {
      "start": "2026-06-29T00:10:00.000Z",
      "end": "2026-06-29T00:15:00.000Z",
      "status": "empty",
      "eventCount": 0,
      "open": null,
      "high": null,
      "low": null,
      "close": null,
      "baseVolumeAtomic": "0",
      "quoteVolumeAtomic": "0"
    },
    {
      "start": "2026-06-29T00:15:00.000Z",
      "end": "2026-06-29T00:20:00.000Z",
      "status": "empty",
      "eventCount": 0,
      "open": null,
      "high": null,
      "low": null,
      "close": null,
      "baseVolumeAtomic": "0",
      "quoteVolumeAtomic": "0"
    },
    {
      "start": "2026-06-29T00:20:00.000Z",
      "end": "2026-06-29T00:25:00.000Z",
      "status": "filled",
      "eventCount": 14,
      "open": "0.01082",
      "high": "0.01082",
      "low": "0.01077",
      "close": "0.01077",
      "baseVolumeAtomic": "6293600000",
      "quoteVolumeAtomic": "67914398"
    },
    {
      "start": "2026-06-29T00:25:00.000Z",
      "end": "2026-06-29T00:30:00.000Z",
      "status": "filled",
      "eventCount": 10,
      "open": "0.01082",
      "high": "0.01082",
      "low": "0.01077",
      "close": "0.01077",
      "baseVolumeAtomic": "2743600000",
      "quoteVolumeAtomic": "29657448"
    },
    {
      "start": "2026-06-29T00:30:00.000Z",
      "end": "2026-06-29T00:35:00.000Z",
      "status": "filled",
      "eventCount": 73,
      "open": "0.01082",
      "high": "0.01082",
      "low": "0.01076",
      "close": "0.01081",
      "baseVolumeAtomic": "43136000000",
      "quoteVolumeAtomic": "465229708"
    },
    {
      "start": "2026-06-29T00:35:00.000Z",
      "end": "2026-06-29T00:40:00.000Z",
      "status": "empty",
      "eventCount": 0,
      "open": null,
      "high": null,
      "low": null,
      "close": null,
      "baseVolumeAtomic": "0",
      "quoteVolumeAtomic": "0"
    },
    {
      "start": "2026-06-29T00:40:00.000Z",
      "end": "2026-06-29T00:45:00.000Z",
      "status": "empty",
      "eventCount": 0,
      "open": null,
      "high": null,
      "low": null,
      "close": null,
      "baseVolumeAtomic": "0",
      "quoteVolumeAtomic": "0"
    },
    {
      "start": "2026-06-29T00:45:00.000Z",
      "end": "2026-06-29T00:50:00.000Z",
      "status": "empty",
      "eventCount": 0,
      "open": null,
      "high": null,
      "low": null,
      "close": null,
      "baseVolumeAtomic": "0",
      "quoteVolumeAtomic": "0"
    },
    {
      "start": "2026-06-29T00:50:00.000Z",
      "end": "2026-06-29T00:55:00.000Z",
      "status": "filled",
      "eventCount": 10,
      "open": "0.01083",
      "high": "0.01088",
      "low": "0.01083",
      "close": "0.01083",
      "baseVolumeAtomic": "5558200000",
      "quoteVolumeAtomic": "60224651"
    },
    {
      "start": "2026-06-29T00:55:00.000Z",
      "end": "2026-06-29T01:00:00.000Z",
      "status": "filled",
      "eventCount": 37,
      "open": "0.01083",
      "high": "0.01088",
      "low": "0.01083",
      "close": "0.01084",
      "baseVolumeAtomic": "21797300000",
      "quoteVolumeAtomic": "236160852"
    },
    {
      "start": "2026-06-29T01:00:00.000Z",
      "end": "2026-06-29T01:05:00.000Z",
      "status": "empty",
      "eventCount": 0,
      "open": null,
      "high": null,
      "low": null,
      "close": null,
      "baseVolumeAtomic": "0",
      "quoteVolumeAtomic": "0"
    },
    {
      "start": "2026-06-29T01:05:00.000Z",
      "end": "2026-06-29T01:10:00.000Z",
      "status": "empty",
      "eventCount": 0,
      "open": null,
      "high": null,
      "low": null,
      "close": null,
      "baseVolumeAtomic": "0",
      "quoteVolumeAtomic": "0"
    },
    {
      "start": "2026-06-29T01:10:00.000Z",
      "end": "2026-06-29T01:15:00.000Z",
      "status": "empty",
      "eventCount": 0,
      "open": null,
      "high": null,
      "low": null,
      "close": null,
      "baseVolumeAtomic": "0",
      "quoteVolumeAtomic": "0"
    }
  ]
}
