{
  "schemaVersion": 1,
  "pairId": "USDSUI_USDC",
  "week": {
    "weekYear": 2026,
    "week": 26,
    "startsAt": "2026-06-22T00:00:00.000Z",
    "endsAt": "2026-06-29T00:00:00.000Z",
    "timeZone": "UTC"
  },
  "barIntervalMinutes": 10,
  "priceConvention": "USDC_PER_BASE",
  "disclaimer": "USDC is a token-denominated reference asset in this index. It is not fiat USD and this repository does not guarantee a USDC/USD peg.",
  "bars": [
    {
      "start": "2026-06-26T17:10:00.000Z",
      "end": "2026-06-26T17:20:00.000Z",
      "status": "filled",
      "eventCount": 19,
      "open": "0.999493978937",
      "high": "0.999493998194",
      "low": "0.999249997176",
      "close": "0.999355993962",
      "baseVolumeAtomic": "1024720000",
      "quoteVolumeAtomic": "1024073064"
    },
    {
      "start": "2026-06-26T17:20:00.000Z",
      "end": "2026-06-26T17:30:00.000Z",
      "status": "filled",
      "eventCount": 15,
      "open": "0.999493991807",
      "high": "0.999493996494",
      "low": "0.99924999281",
      "close": "0.999493993152",
      "baseVolumeAtomic": "676420000",
      "quoteVolumeAtomic": "676009559"
    },
    {
      "start": "2026-06-26T17:30:00.000Z",
      "end": "2026-06-26T17:40:00.000Z",
      "status": "filled",
      "eventCount": 35,
      "open": "0.999355996491",
      "high": "0.999493996415",
      "low": "0.999249988165",
      "close": "0.99935599915",
      "baseVolumeAtomic": "5517300000",
      "quoteVolumeAtomic": "5513260836"
    },
    {
      "start": "2026-06-26T17:40:00.000Z",
      "end": "2026-06-26T17:50:00.000Z",
      "status": "filled",
      "eventCount": 27,
      "open": "0.999493996789",
      "high": "0.999493996789",
      "low": "0.999249994644",
      "close": "0.999493973471",
      "baseVolumeAtomic": "4125460000",
      "quoteVolumeAtomic": "4122464531"
    },
    {
      "start": "2026-06-26T17:50:00.000Z",
      "end": "2026-06-26T18:00:00.000Z",
      "status": "filled",
      "eventCount": 16,
      "open": "0.999493979671",
      "high": "0.999493989731",
      "low": "0.999175975422",
      "close": "0.999355984397",
      "baseVolumeAtomic": "691250000",
      "quoteVolumeAtomic": "690819999"
    },
    {
      "start": "2026-06-26T18:00:00.000Z",
      "end": "2026-06-26T18:10:00.000Z",
      "status": "filled",
      "eventCount": 19,
      "open": "0.999493977305",
      "high": "0.999493998908",
      "low": "0.99925",
      "close": "0.999493993993",
      "baseVolumeAtomic": "1410650000",
      "quoteVolumeAtomic": "1409707117"
    },
    {
      "start": "2026-06-26T18:10:00.000Z",
      "end": "2026-06-26T18:20:00.000Z",
      "status": "filled",
      "eventCount": 23,
      "open": "0.999355993852",
      "high": "0.999493994622",
      "low": "0.999249992054",
      "close": "0.999249992054",
      "baseVolumeAtomic": "2418330000",
      "quoteVolumeAtomic": "2416623286"
    },
    {
      "start": "2026-06-26T18:20:00.000Z",
      "end": "2026-06-26T18:30:00.000Z",
      "status": "filled",
      "eventCount": 44,
      "open": "0.999355991124",
      "high": "0.999493999456",
      "low": "0.999249920508",
      "close": "0.999493997208",
      "baseVolumeAtomic": "8019150000",
      "quoteVolumeAtomic": "8013259814"
    },
    {
      "start": "2026-06-26T18:30:00.000Z",
      "end": "2026-06-26T18:40:00.000Z",
      "status": "filled",
      "eventCount": 24,
      "open": "0.99935599268",
      "high": "0.99949398991",
      "low": "0.999247977582",
      "close": "0.999247977582",
      "baseVolumeAtomic": "5181000000",
      "quoteVolumeAtomic": "5177186586"
    },
    {
      "start": "2026-06-26T18:40:00.000Z",
      "end": "2026-06-26T18:50:00.000Z",
      "status": "filled",
      "eventCount": 18,
      "open": "0.999386999679",
      "high": "0.999493994585",
      "low": "0.999248",
      "close": "0.999493993737",
      "baseVolumeAtomic": "686780000",
      "quoteVolumeAtomic": "686362508"
    },
    {
      "start": "2026-06-26T18:50:00.000Z",
      "end": "2026-06-26T19:00:00.000Z",
      "status": "filled",
      "eventCount": 26,
      "open": "0.999355988792",
      "high": "0.999494",
      "low": "0.999249997004",
      "close": "0.999355981695",
      "baseVolumeAtomic": "3932630000",
      "quoteVolumeAtomic": "3929780816"
    },
    {
      "start": "2026-06-26T19:00:00.000Z",
      "end": "2026-06-26T19:10:00.000Z",
      "status": "filled",
      "eventCount": 23,
      "open": "0.999493976814",
      "high": "1.00008192771",
      "low": "0.999068974901",
      "close": "1.00008192771",
      "baseVolumeAtomic": "3315340000",
      "quoteVolumeAtomic": "3313138649"
    },
    {
      "start": "2026-06-26T19:10:00.000Z",
      "end": "2026-06-26T19:20:00.000Z",
      "status": "filled",
      "eventCount": 24,
      "open": "0.999604988886",
      "high": "1.000078",
      "low": "0.999249972987",
      "close": "0.99925",
      "baseVolumeAtomic": "1326080000",
      "quoteVolumeAtomic": "1325316678"
    },
    {
      "start": "2026-06-26T19:20:00.000Z",
      "end": "2026-06-26T19:30:00.000Z",
      "status": "filled",
      "eventCount": 27,
      "open": "0.999750988915",
      "high": "0.999750988915",
      "low": "0.999249996241",
      "close": "0.999619982038",
      "baseVolumeAtomic": "3172970000",
      "quoteVolumeAtomic": "3170850205"
    },
    {
      "start": "2026-06-26T19:30:00.000Z",
      "end": "2026-06-26T19:40:00.000Z",
      "status": "filled",
      "eventCount": 16,
      "open": "0.999758989997",
      "high": "0.999758989997",
      "low": "0.99925",
      "close": "0.999541985723",
      "baseVolumeAtomic": "601710000",
      "quoteVolumeAtomic": "601475659"
    },
    {
      "start": "2026-06-26T19:40:00.000Z",
      "end": "2026-06-26T19:50:00.000Z",
      "status": "filled",
      "eventCount": 17,
      "open": "0.999680983877",
      "high": "0.999734994285",
      "low": "0.999249999198",
      "close": "0.999675",
      "baseVolumeAtomic": "1839260000",
      "quoteVolumeAtomic": "1838083895"
    },
    {
      "start": "2026-06-26T19:50:00.000Z",
      "end": "2026-06-26T20:00:00.000Z",
      "status": "filled",
      "eventCount": 39,
      "open": "0.999674977843",
      "high": "0.999737986743",
      "low": "0.99924990689",
      "close": "0.999522984108",
      "baseVolumeAtomic": "8907820000",
      "quoteVolumeAtomic": "8901301472"
    },
    {
      "start": "2026-06-26T20:00:00.000Z",
      "end": "2026-06-26T20:10:00.000Z",
      "status": "filled",
      "eventCount": 20,
      "open": "0.999249693251",
      "high": "0.99969898399",
      "low": "0.999233333333",
      "close": "0.999559983831",
      "baseVolumeAtomic": "2198570000",
      "quoteVolumeAtomic": "2197098839"
    },
    {
      "start": "2026-06-26T20:10:00.000Z",
      "end": "2026-06-26T20:20:00.000Z",
      "status": "filled",
      "eventCount": 30,
      "open": "0.99956",
      "high": "0.999698995271",
      "low": "0.999249991698",
      "close": "0.999629997941",
      "baseVolumeAtomic": "5460500000",
      "quoteVolumeAtomic": "5456570209"
    },
    {
      "start": "2026-06-26T20:20:00.000Z",
      "end": "2026-06-26T20:30:00.000Z",
      "status": "filled",
      "eventCount": 16,
      "open": "0.999491973532",
      "high": "0.999730982048",
      "low": "0.999249998052",
      "close": "0.999249998052",
      "baseVolumeAtomic": "2719910000",
      "quoteVolumeAtomic": "2718040259"
    },
    {
      "start": "2026-06-26T20:30:00.000Z",
      "end": "2026-06-26T20:40:00.000Z",
      "status": "filled",
      "eventCount": 32,
      "open": "0.999249999369",
      "high": "0.999722994798",
      "low": "0.999249988901",
      "close": "0.999697978303",
      "baseVolumeAtomic": "6657820000",
      "quoteVolumeAtomic": "6653013533"
    },
    {
      "start": "2026-06-26T20:40:00.000Z",
      "end": "2026-06-26T20:50:00.000Z",
      "status": "filled",
      "eventCount": 15,
      "open": "0.999558978759",
      "high": "0.999711987226",
      "low": "0.99924997022",
      "close": "0.999526981891",
      "baseVolumeAtomic": "555160000",
      "quoteVolumeAtomic": "554933693"
    },
    {
      "start": "2026-06-26T20:50:00.000Z",
      "end": "2026-06-26T21:00:00.000Z",
      "status": "filled",
      "eventCount": 12,
      "open": "0.999611976047",
      "high": "0.99974399449",
      "low": "0.999588975718",
      "close": "0.999605986787",
      "baseVolumeAtomic": "505330000",
      "quoteVolumeAtomic": "505153603"
    },
    {
      "start": "2026-06-26T21:00:00.000Z",
      "end": "2026-06-26T21:10:00.000Z",
      "status": "filled",
      "eventCount": 10,
      "open": "0.999736981446",
      "high": "0.999743997286",
      "low": "0.999249997022",
      "close": "0.999655989159",
      "baseVolumeAtomic": "708970000",
      "quoteVolumeAtomic": "708561010"
    }
  ]
}
